cli_tool/__init__.py
cli_tool/cli_generate_pydantic.py
fastapi_crud_tortoise/__init__.pyc
fastapi_crud_tortoise/__init__.pyi
fastapi_crud_tortoise/_base.pyc
fastapi_crud_tortoise/_base.pyi
fastapi_crud_tortoise/_model.pyc
fastapi_crud_tortoise/_model.pyi
fastapi_crud_tortoise/_tortoise_convert.pyc
fastapi_crud_tortoise/_tortoise_convert.pyi
fastapi_crud_tortoise/_types.pyc
fastapi_crud_tortoise/_types.pyi
fastapi_crud_tortoise/_utils.pyc
fastapi_crud_tortoise/_utils.pyi
fastapi_crud_tortoise/src/__init__.pyc
fastapi_crud_tortoise/src/__init__.pyi
fastapi_crud_tortoise/src/_files.pyc
fastapi_crud_tortoise/src/_files.pyi
fastapi_crud_tortoise/src/_gen_excel.pyc
fastapi_crud_tortoise/src/_gen_excel.pyi
fastapi_crud_tortoise/src/_settings.pyc
fastapi_crud_tortoise/src/_settings.pyi
fastapi_crud_tortoise/src/_tortoise_crud.pyc
fastapi_crud_tortoise/src/_tortoise_crud.pyi
tests/__init__.py
tests/demo.py
tests/models/dummy.py
wh_fastapi_crud_tortoise-0.1.29.dist-info/METADATA
wh_fastapi_crud_tortoise-0.1.29.dist-info/WHEEL
wh_fastapi_crud_tortoise-0.1.29.dist-info/entry_points.txt
wh_fastapi_crud_tortoise-0.1.29.dist-info/top_level.txt
wh_fastapi_crud_tortoise-0.1.29.dist-info/RECORD
