Metadata-Version: 2.2
Name: wh_fastapi_crud_tortoise
Version: 0.1.29
Summary: A CRUD library for Tortoise ORM
Home-page: https://github.com/kanbang/fastapi-crud-pro
Author: kanbang
Author-email: kanbang@163.com
Project-URL: Bug Reports, https://github.com/kanbang/fastapi-crud-pro/issues
Project-URL: Source, https://github.com/kanbang/fastapi-crud-pro
Keywords: crud,tortoise-orm,sqlalchemy,database
Classifier: Development Status :: 3 - Alpha
Classifier: Intended Audience :: Developers
Classifier: License :: OSI Approved :: MIT License
Classifier: Operating System :: OS Independent
Classifier: Programming Language :: Python :: 3.10
Classifier: Programming Language :: Python :: 3.11
Classifier: Programming Language :: Python :: 3.12
Classifier: Programming Language :: Python :: 3.13
Requires-Python: >=3.10
Requires-Dist: tortoise-orm>=0.20.1
Requires-Dist: pydantic>=2.7.1
Requires-Dist: openpyxl>=3.1.5
Dynamic: author
Dynamic: author-email
Dynamic: classifier
Dynamic: description
Dynamic: description-content-type
Dynamic: home-page
Dynamic: keywords
Dynamic: project-url
Dynamic: requires-dist
Dynamic: requires-python
Dynamic: summary
